{
  "run_id": "20260603-135931",
  "timestamp": 1780513171.8938708,
  "solution": "solutions/hashgrid_bb_m.py",
  "name": "hashgrid_bb_m",
  "description": "hash grid (24 lvl, F=2, T=2^23, Nmax=8192) + MLP 256x4, adaptive mining + batch 524k + table LR 4e-1 + MLP LR 1.5e-2",
  "commit": "e4e7edf",
  "device": "NVIDIA GeForce RTX 3090 Ti",
  "status": "ok",
  "train_seconds": 300.2053619779999,
  "mse": 0.00044124526903033257,
  "mae": 0.0026593597140163183,
  "psnr": 33.553199380234645,
  "boundary_mse": 0.0004728281928692013
}